dtale_desktop/__init__.py
dtale_desktop/actions.py
dtale_desktop/app.py
dtale_desktop/dtale_app.py
dtale_desktop/file_system.py
dtale_desktop/logger.py
dtale_desktop/models.py
dtale_desktop/pydantic_utils.py
dtale_desktop/settings.py
dtale_desktop/source_code_tools.py
dtale_desktop/subprocesses.py
dtale_desktop/websocket_connections.py
dtale_desktop/z_downloads.py
dtale_desktop/default_sources/__init__.py
dtale_desktop/default_sources/dft_csv/__init__.py
dtale_desktop/default_sources/dft_csv/get_data.py
dtale_desktop/default_sources/dft_csv/list_paths.py
dtale_desktop/default_sources/dft_csv/metadata.py
dtale_desktop/default_sources/dft_excel/__init__.py
dtale_desktop/default_sources/dft_excel/get_data.py
dtale_desktop/default_sources/dft_excel/list_paths.py
dtale_desktop/default_sources/dft_excel/metadata.py
dtale_desktop/default_sources/dft_json/__init__.py
dtale_desktop/default_sources/dft_json/get_data.py
dtale_desktop/default_sources/dft_json/list_paths.py
dtale_desktop/default_sources/dft_json/metadata.py
dtale_desktop/frontend/build/asset-manifest.json
dtale_desktop/frontend/build/favicon.ico
dtale_desktop/frontend/build/index.html
dtale_desktop/frontend/build/logo192.png
dtale_desktop/frontend/build/logo512.png
dtale_desktop/frontend/build/manifest.json
dtale_desktop/frontend/build/precache-manifest.50a948b550e88d454f33ad09bc837d96.js
dtale_desktop/frontend/build/precache-manifest.ed5eecf90f1d266295b199ce1ca192e4.js
dtale_desktop/frontend/build/robots.txt
dtale_desktop/frontend/build/service-worker.js
dtale_desktop/frontend/build/static/css/main.5ecd60fb.chunk.css
dtale_desktop/frontend/build/static/css/main.5ecd60fb.chunk.css.map
dtale_desktop/frontend/build/static/js/2.9e8dd5df.chunk.js
dtale_desktop/frontend/build/static/js/2.9e8dd5df.chunk.js.LICENSE.txt
dtale_desktop/frontend/build/static/js/2.9e8dd5df.chunk.js.map
dtale_desktop/frontend/build/static/js/main.4dca97fd.chunk.js
dtale_desktop/frontend/build/static/js/main.4dca97fd.chunk.js.map
dtaledesktop-0.1.3.dist-info/LICENSE.md
dtaledesktop-0.1.3.dist-info/METADATA
dtaledesktop-0.1.3.dist-info/WHEEL
dtaledesktop-0.1.3.dist-info/entry_points.txt
dtaledesktop-0.1.3.dist-info/top_level.txt
dtaledesktop-0.1.3.dist-info/RECORD
