Metadata-Version: 2.1
Name: dtaledesktop
Version: 0.1.3
Summary: Build a data visualization dashboard with simple snippets of python code
Home-page: https://github.com/phillipdupuis/dtale-desktop
Author: Phillip Dupuis
Author-email: phillip_dupuis@alumni.brown.edu
License: MIT
Keywords: dtale,visualization,pandas
Platform: UNKNOWN
Classifier: Development Status :: 4 - Beta
Classifier: License :: OSI Approved :: MIT License
Classifier: Programming Language :: Python
Classifier: Programming Language :: Python :: 3
Classifier: Programming Language :: Python :: 3 :: Only
Classifier: Programming Language :: Python :: 3.6
Classifier: Programming Language :: Python :: 3.7
Classifier: Programming Language :: Python :: 3.8
Classifier: Programming Language :: Python :: 3.9
Requires-Dist: dtale (>=1.22.1)
Requires-Dist: fastapi
Requires-Dist: uvicorn[standard]
Requires-Dist: aiofiles
Requires-Dist: aiohttp
Requires-Dist: typing-extensions
Requires-Dist: pandas-profiling
